thg/__init__.py
thg/toplevel.py
thglib/__init__.py
thglib/version.py
thglib/teste/Test.py
thglib/teste/__init__.py
thglib-0.0.2.dev0.data/data/thglib-doc/CHANGELOG.md
thglib-0.0.2.dev0.data/data/thglib-doc/CONTRIBUTING.md
thglib-0.0.2.dev0.data/data/thglib-doc/LICENSE-thglib.txt
thglib-0.0.2.dev0.data/data/thglib-doc/README.md
thglib-0.0.2.dev0.data/data/thglib-doc/TESTING.md
thglib-0.0.2.dev0.data/data/thglib-doc/requirements.txt
thglib-0.0.2.dev0.dist-info/LICENSE-thglib.txt
thglib-0.0.2.dev0.dist-info/METADATA
thglib-0.0.2.dev0.dist-info/WHEEL
thglib-0.0.2.dev0.dist-info/entry_points.txt
thglib-0.0.2.dev0.dist-info/top_level.txt
thglib-0.0.2.dev0.dist-info/RECORD
