Metadata-Version: 2.1
Name: thglib
Version: 0.0.2.dev0
Summary: thg exploit framework and exploit development library.
Home-page: https://darkcode0x00/thg
Author: Gallopsled et al.
Author-email: darkcode357@gmail.com
License: Mostly MIT, some GPL/BSD, see LICENSE-thglib.txt
Download-URL: https://github.com/THGFramework/thg-framework
Keywords: thg exploit ctf capture the flag binary wargame overflow stack heap
Platform: UNKNOWN
Classifier: Development Status :: 5 - Production/Stable
Classifier: Environment :: Console
Classifier: Intended Audience :: Developers
Classifier: Intended Audience :: Science/Research
Classifier: Intended Audience :: System Administrators
Classifier: License :: OSI Approved :: MIT License
Classifier: Natural Language :: English
Classifier: Operating System :: POSIX :: Linux
Classifier: Programming Language :: Python :: 2.7
Classifier: Programming Language :: Python :: 3
Classifier: Topic :: Security
Classifier: Topic :: Software Development :: Assemblers
Classifier: Topic :: Software Development :: Debuggers
Classifier: Topic :: Software Development :: Disassemblers
Classifier: Topic :: Software Development :: Embedded Systems
Classifier: Topic :: Software Development :: Libraries :: Python Modules
Classifier: Topic :: System :: System Shells
Classifier: Topic :: Utilities
Requires-Python: >=2.7
Requires-Dist: paramiko (>=1.15.2)
Requires-Dist: mako (>=1.0.0)
Requires-Dist: pyelftools (>=0.2.4)
Requires-Dist: capstone (>=3.0.5rc2ropgadget>=5.3)
Requires-Dist: pyserial (>=2.7)
Requires-Dist: requests (>=2.0)
Requires-Dist: pip (>=6.0.8)
Requires-Dist: pygments (>=2.0)
Requires-Dist: pysocks
Requires-Dist: python-dateutil
Requires-Dist: packaging
Requires-Dist: psutil (>=3.3.0)
Requires-Dist: intervaltree (>=3.0)
Requires-Dist: sortedcontainers
Requires-Dist: unicorn (<1.0.2rc4six>=1.12.0,>=1.0.2rc1)
Requires-Dist: rpyc
Requires-Dist: colored-traceback
